float_to_ascii.v
module float_to_ascii(
    input  wire signed [15:0] val_100,   // scaled by 100
    output reg  [7:0] ch0,               // sign  ('-', '+', or ' ')
    output reg  [7:0] ch1,               // hundreds
    output reg  [7:0] ch2,               // tens
    output reg  [7:0] ch3,               // ones
    output reg  [7:0] ch4,               // '.'
    output reg  [7:0] ch5,               // tenths
    output reg  [7:0] ch6                // hundredths
);

    reg signed [15:0] tmp;
    reg [15:0] mag;           // absolute value
    reg [13:0] int_part;      // integer part (0..999)
    reg [6:0]  frac_part;     // 0..99

    reg [3:0] hundreds;
    reg [3:0] tens;
    reg [3:0] ones;
    reg [3:0] frac_tens;
    reg [3:0] frac_ones;

    always @* begin
        tmp = val_100;

        // sign
        if (tmp < 0) begin
            ch0 = "-";
            mag = -tmp;
        end else begin
            ch0 = " ";   // or "+" if you prefer
            mag = tmp;
        end

        // split into integer and fractional parts
        int_part  = mag / 100;   // integer portion
        frac_part = mag % 100;   // 0..99

        // clamp range to 0..999 just in case
        if (int_part > 999)
            int_part = 999;

        // integer digits
        hundreds = int_part / 100;
        tens     = (int_part / 10) % 10;
        ones     = int_part % 10;

        // fractional digits (two decimal places)
        frac_tens = frac_part / 10;
        frac_ones = frac_part % 10;

        // map digits to ASCII '0'..'9'
        ch1 = "0" + hundreds;
        ch2 = "0" + tens;
        ch3 = "0" + ones;

        ch4 = ".";

        ch5 = "0" + frac_tens;
        ch6 = "0" + frac_ones;
    end

endmodule

gcode_sender.v
module gcode_sender(
    input wire [31:0] xo,
    input wire [31:0] xt,
    input wire [31:0] yo,
    input wire [31:0] yt,
    input wire [1:0] intensity,
    input wire g_send,
    output wire g_busy,
    input wire clk,
    input wire reset,
    input wire tx_ready,
    output reg tx_valid = 0,
    output reg [7:0] tx_data = 0
);


    reg [1:0] state = 2'b00;

    localparam START = 2'b00;
    localparam IDLE = 2'b01;
    localparam SENDING = 2'b10;

    assign g_busy = (state != IDLE);

    // reg [7:0] gcode_bytes [0:17];
    reg [8:0] index = 0;
    reg first_cycle = 1'b1;
    reg start_up = 1'b1;
    reg prev_ready = 0;
    reg see_ready = 0;
    reg [8*64-1:0] startup = "\n0Z 0Y 0X 29G\n45G 49G 71G 12G 09G";

    reg [7:0] g_value = "0";
    reg [7:0] [7:0] x_ascii;
    reg [7:0] [7:0] y_ascii;
    reg [8*64-1:0] g_output;
    reg [3:0] [7:0] z_value;

    float_to_ascii x_value(.val_100((xt - xo)*100), 
                            .ch0(x_ascii[6]), 
                            .ch1(x_ascii[5]),
                            .ch2(x_ascii[4]),
                            .ch3(x_ascii[3]),
                            .ch4(x_ascii[2]), 
                            .ch5(x_ascii[1]),
                            .ch6(x_ascii[0]));
    float_to_ascii y_value(.val_100((yt - yo)*100), 
                            .ch0(y_ascii[6]), 
                            .ch1(y_ascii[5]),
                            .ch2(y_ascii[4]),
                            .ch3(y_ascii[3]),
                            .ch4(y_ascii[2]), 
                            .ch5(y_ascii[1]),
                            .ch6(y_ascii[0]));


    always @(posedge clk) begin
        if(intensity == 0)begin
            g_value <= "1";
        end else begin
            g_value <= "0";
        end
        case(intensity)
            2'b00: begin
                z_value[0] <= "0";
                z_value[1] <= "0";
                z_value[2] <= ".";
                z_value[3] <= "2";
            end
            2'b01: begin
                z_value[0] <= "0";
                z_value[1] <= "6";
                z_value[2] <= ".";
                z_value[3] <= "0";
            end
            2'b10: begin
                z_value[0] <= "0";
                z_value[1] <= "3";
                z_value[2] <= ".";
                z_value[3] <= "0";
            end
            2'b11: begin
                z_value[0] <= "0";
                z_value[1] <= "0";
                z_value[2] <= ".";
                z_value[3] <= "0";
            end

        endcase
    end
    always @(posedge clk) begin
        g_output = {"\n0001F ", 
                    z_value[0], 
                    z_value[1], 
                    z_value[2], 
                    z_value[3], 
                    "Z " , 
                    y_ascii[0], 
                    y_ascii[1], 
                    y_ascii[2], 
                    y_ascii[3], 
                    y_ascii[4], 
                    y_ascii[5], 
                    y_ascii[6],
                    "Y " , 
                    x_ascii[0], 
                    x_ascii[1], 
                    x_ascii[2], 
                    x_ascii[3], 
                    x_ascii[4], 
                    x_ascii[5], 
                    x_ascii[6], 
                    "X " , 
                    g_value , 
                    "G"};
    end

    always @(posedge clk) begin
        if(reset)begin
            index <= 0;
            tx_valid <=0;
            state <= START;
        end else begin
            case(state)
                START: begin
                    tx_valid <=0;
                    if (see_ready) begin
                        tx_valid <= 1;
                        index <= index + 1;
                        tx_data <= startup[8*index +: 8];
                    end
                    if(see_ready && index == 63)begin
                        state <= IDLE;
                    end
                end
                IDLE: begin
                    index <=0;
                    if(g_send)begin
                        state <= SENDING;
                    end
                end
                SENDING: begin
                    tx_valid <=0;
                    if (see_ready) begin
                        tx_valid <= 1;
                        index <= index + 1;
                        tx_data <= g_output[8*index +: 8];
                    end
                    if(see_ready && index == 63)begin
                        state <= IDLE;
                    end
                end
            endcase
        end
    end

    always @(posedge clk) begin
        prev_ready <= tx_ready;
        if(first_cycle) begin
            see_ready <= tx_ready;
            first_cycle <=0;
        end else begin
            see_ready <= ~prev_ready & tx_ready;
        end
    end

endmodule

uart_transmit.v
module uart_transmit #(
    parameter CLK_HZ = 100_000_000,
    parameter BAUD_RT = 115200,
    parameter DATA_BITS = 8
)(
    input wire clk,
    input wire reset,
    output wire tx_send,
    output wire tx_busy,
    input wire tx_start,
    input wire [7:0] tx_data,
    input wire rx
);
    localparam CYCLES_PER_BIT = CLK_HZ/BAUD_RT;
    localparam COUNT_CYC_BITS = $clog2(CYCLES_PER_BIT);
    // assign baud_clk = BAUD_CLK;
    reg BAUD_CLK = 0;
    reg [COUNT_CYC_BITS-1:0] cycle_counter = 0;
    reg [1:0] state = IDLE;
    reg [3:0] bit_counter;
    reg [7:0] shifted_data;
    reg tx_sdata = 1'b1;

    assign tx_send = tx_sdata;
    assign tx_busy = (state != IDLE);

    localparam IDLE = 2'b00;
    localparam START = 2'b01;
    localparam DATA = 2'b10;
    localparam STOP = 2'b11;

    always @(posedge clk) begin
        if (reset) begin
            cycle_counter <= 0;
            BAUD_CLK <= 0;
        end else begin
            if(cycle_counter == (CYCLES_PER_BIT -1)) begin
                cycle_counter <= 0;
                BAUD_CLK <= 1;
            end else begin
                cycle_counter <= cycle_counter +1;
                BAUD_CLK <= 0;
            end
        end
    end

    always @(posedge clk) begin
        if (reset) begin
            bit_counter <= 0;
            tx_sdata <= 1;
            state <= IDLE;
        end else begin
        case (state) 
            IDLE: begin
                bit_counter <= 0;
                if(tx_start)begin
                    shifted_data <= tx_data;
                    state <= START;
                end
            end
            START: begin
                if(BAUD_CLK) begin
                    tx_sdata <= 1'b0;
                    state <= DATA;
                end
            end
            DATA: begin
                if(BAUD_CLK) begin
                    tx_sdata <= shifted_data[0];
                    shifted_data <= {1'b0, shifted_data[7:1]};
                    if(bit_counter == 7) begin
                        state <= STOP;
                        bit_counter <=0;
                    end else begin
                        bit_counter <= bit_counter +1;
                    end
                end
            end
            STOP: begin
                if(BAUD_CLK) begin
                    tx_sdata <= 1'b1;
                    state <= IDLE;
                end
            end
        endcase
        end
    end

endmodule

sending_tx.v
module sending_tx(
    input wire clk,
    input wire reset,
    input wire BTNU,
    output wire tx
);

    wire uart_tx_busy;
    wire tx_valid;
    wire baud_clk;
    reg [31:0] xo, xt, yo, yt;
    reg [1:0] intensity;
    reg g_send;
    wire g_busy;

    wire[7:0] test_letter;
    reg bup;
    always @(posedge clk) begin
        bup = BTNU;
    end
    always @(posedge bup) begin
        if(!g_busy)begin
            xo = 0;
            xt = 0;
            yo = 0;
            yt = 10;
            intensity = 0;
            g_send <=0;
        end
    end

    uart_transmit uut(.clk(clk), 
            .reset(reset), 
            .tx_send(tx), 
            .tx_busy(uart_tx_busy), 
            .tx_start(tx_valid), 
            .tx_data(test_letter));

    gcode_sender getting_gcode(
        .xo(xo),
        .xt(xt),
        .yo(yo),
        .yt(yt),
        .intensity(intensity),
        .g_send(g_send),
        .g_busy(g_busy),
        .clk(clk),
        .reset(reset),
        .tx_ready(!uart_tx_busy),
        .tx_valid(tx_valid),
        .tx_data(test_letter));
endmodule

send_tx_tb.v
`timescale 1ns/1ps

module send_tx_tb;
    reg clk, reset, BTNU;
    wire tx, rx;

    sending_tx transmitTest(.clk(clk), .reset(reset), .tx(tx), .BTNU(BTNU));

    initial begin
        clk = 0;
        forever #5 clk = ~clk;
    end
    initial begin
        BTNU = 0;
        repeat(20) @(posedge clk);
        BTNU = 1;
        repeat (5) @(posedge clk);
        BTNU = 0;
    end
    initial begin
        #1000000;
        $finish;
    end
    initial begin
        $dumpfile("sending_tx.vcd");
        $dumpvars(0, send_tx_tb);
    end

endmodule

sending_tx.vcd
$date
	Thu Dec  4 20:51:02 2025
$end
$version
	Icarus Verilog
$end
$timescale
	1ps
$end
$scope module send_tx_tb $end
$var wire 1 ! tx $end
$var reg 1 " BTNU $end
$var reg 1 # clk $end
$var reg 1 $ reset $end
$scope module transmitTest $end
$var wire 1 " BTNU $end
$var wire 1 # clk $end
$var wire 1 $ reset $end
$var wire 1 % uart_tx_busy $end
$var wire 1 & tx_valid $end
$var wire 1 ! tx $end
$var wire 8 ' test_letter [7:0] $end
$var wire 1 ( g_busy $end
$var reg 1 ) bup $end
$var reg 1 * g_send $end
$var reg 2 + intensity [1:0] $end
$var reg 32 , xo [31:0] $end
$var reg 32 - xt [31:0] $end
$var reg 32 . yo [31:0] $end
$var reg 32 / yt [31:0] $end
$scope module getting_gcode $end
$var wire 1 # clk $end
$var wire 1 * g_send $end
$var wire 2 0 intensity [1:0] $end
$var wire 1 $ reset $end
$var wire 1 1 tx_ready $end
$var wire 32 2 xo [31:0] $end
$var wire 32 3 xt [31:0] $end
$var wire 32 4 yo [31:0] $end
$var wire 32 5 yt [31:0] $end
$var wire 64 6 y_ascii [63:0] $end
$var wire 64 7 x_ascii [63:0] $end
$var wire 1 ( g_busy $end
$var parameter 2 8 IDLE $end
$var parameter 2 9 SENDING $end
$var parameter 2 : START $end
$var reg 1 ; first_cycle $end
$var reg 512 < g_output [511:0] $end
$var reg 8 = g_value [7:0] $end
$var reg 9 > index [8:0] $end
$var reg 1 ? prev_ready $end
$var reg 1 @ see_ready $end
$var reg 1 A start_up $end
$var reg 512 B startup [511:0] $end
$var reg 2 C state [1:0] $end
$var reg 8 D tx_data [7:0] $end
$var reg 1 & tx_valid $end
$var reg 32 E z_value [31:0] $end
$scope module x_value $end
$var wire 16 F val_100 [15:0] $end
$var reg 8 G ch0 [7:0] $end
$var reg 8 H ch1 [7:0] $end
$var reg 8 I ch2 [7:0] $end
$var reg 8 J ch3 [7:0] $end
$var reg 8 K ch4 [7:0] $end
$var reg 8 L ch5 [7:0] $end
$var reg 8 M ch6 [7:0] $end
$var reg 4 N frac_ones [3:0] $end
$var reg 7 O frac_part [6:0] $end
$var reg 4 P frac_tens [3:0] $end
$var reg 4 Q hundreds [3:0] $end
$var reg 14 R int_part [13:0] $end
$var reg 16 S mag [15:0] $end
$var reg 4 T ones [3:0] $end
$var reg 4 U tens [3:0] $end
$var reg 16 V tmp [15:0] $end
$upscope $end
$scope module y_value $end
$var wire 16 W val_100 [15:0] $end
$var reg 8 X ch0 [7:0] $end
$var reg 8 Y ch1 [7:0] $end
$var reg 8 Z ch2 [7:0] $end
$var reg 8 [ ch3 [7:0] $end
$var reg 8 \ ch4 [7:0] $end
$var reg 8 ] ch5 [7:0] $end
$var reg 8 ^ ch6 [7:0] $end
$var reg 4 _ frac_ones [3:0] $end
$var reg 7 ` frac_part [6:0] $end
$var reg 4 a frac_tens [3:0] $end
$var reg 4 b hundreds [3:0] $end
$var reg 14 c int_part [13:0] $end
$var reg 16 d mag [15:0] $end
$var reg 4 e ones [3:0] $end
$var reg 4 f tens [3:0] $end
$var reg 16 g tmp [15:0] $end
$upscope $end
$upscope $end
$scope module uut $end
$var wire 1 # clk $end
$var wire 1 $ reset $end
$var wire 8 h tx_data [7:0] $end
$var wire 1 ! tx_send $end
$var wire 1 & tx_start $end
$var wire 1 % tx_busy $end
$var parameter 32 i BAUD_RT $end
$var parameter 32 j CLK_HZ $end
$var parameter 32 k COUNT_CYC_BITS $end
$var parameter 32 l CYCLES_PER_BIT $end
$var parameter 2 m DATA $end
$var parameter 32 n DATA_BITS $end
$var parameter 2 o IDLE $end
$var parameter 2 p START $end
$var parameter 2 q STOP $end
$var reg 1 r BAUD_CLK $end
$var reg 4 s bit_counter [3:0] $end
$var reg 10 t cycle_counter [9:0] $end
$var reg 8 u shifted_data [7:0] $end
$var reg 2 v state [1:0] $end
$var reg 1 w tx_sdata $end
$upscope $end
$upscope $end
$upscope $end
$enddefinitions $end
$comment Show the parameter values. $end
$dumpall
b11 q
b1 p
b0 o
b1000 n
b10 m
b1101100100 l
b1010 k
b101111101011110000100000000 j
b11100001000000000 i
b0 :
b10 9
b1 8
$end
#0
$dumpvars
1w
b0 v
bx u
b0 t
bx s
0r
b0 h
bx g
bx f
bx e
bx d
bx c
bx b
bx a
bx `
bx _
bx ^
bx ]
bx \
bx [
bx Z
bx Y
bx X
bx W
bx V
bx U
bx T
bx S
bx R
bx Q
bx P
bx O
bx N
bx M
bx L
bx K
bx J
bx I
bx H
bx G
bx F
bx E
b0 D
b0 C
b10100011000001011010001000000011000001011001001000000011000001011000001000000011001000111001010001110000101000110100001101010100011100100000001101000011100101000111001000000011011100110001010001110010000000110001001100100100011100100000001100000011100101000111 B
1A
0@
0?
b0 >
b110000 =
bx <
1;
bzxxxxxxxxxxxxxxxxxxxxxxxxxxxxxxxxxxxxxxxxxxxxxxxxxxxxxxxx 7
bzxxxxxxxxxxxxxxxxxxxxxxxxxxxxxxxxxxxxxxxxxxxxxxxxxxxxxxxx 6
bx 5
bx 4
bx 3
bx 2
11
bx 0
bx /
bx .
bx -
bx ,
bx +
x*
x)
1(
b0 '
0&
0%
x$
0#
0"
1!
$end
#5000
b1 t
b0 s
0;
1@
1?
b1010001100000011000000110000001100010100011000100000xxxxxxxxxxxxxxxxxxxxxxxxxxxxxxxx0101101000100000xxxxxxxxxxxxxxxxxxxxxxxxxxxxxxxxxxxxxxxxxxxxxxxxxxxxxxxx0101100100100000xxxxxxxxxxxxxxxxxxxxxxxxxxxxxxxxxxxxxxxxxxxxxxxxxxxxxxxx01011000001000000011000001000111 <
0)
1#
#10000
0#
#15000
0@
b1000111 '
b1000111 D
b1000111 h
b1 >
1&
b10 t
1#
#20000
0#
#25000
b11 t
01
1%
b1 v
b1000111 u
0&
1#
#30000
0#
#35000
0?
b100 t
1#
#40000
0#
#45000
b101 t
1#
#50000
0#
#55000
b110 t
1#
#60000
0#
#65000
b111 t
1#
#70000
0#
#75000
b1000 t
1#
#80000
0#
#85000
b1001 t
1#
#90000
0#
#95000
b1010 t
1#
#100000
0#
#105000
b1011 t
1#
#110000
0#
#115000
b1100 t
1#
#120000
0#
#125000
b1101 t
1#
#130000
0#
#135000
b1110 t
1#
#140000
0#
#145000
b1111 t
1#
#150000
0#
#155000
b10000 t
1#
#160000
0#
#165000
b10001 t
1#
#170000
0#
#175000
b10010 t
1#
#180000
0#
#185000
b10011 t
1#
#190000
0#
#195000
b10100 t
1"
1#
#200000
0#
#205000
b10101 t
1)
1#
#210000
0#
#215000
b10110 t
1#
#220000
0#
#225000
b10111 t
1#
#230000
0#
#235000
b11000 t
1#
#240000
0#
#245000
b11001 t
0)
0"
1#
#250000
0#
#255000
b11010 t
1#
#260000
0#
#265000
b11011 t
1#
#270000
0#
#275000
b11100 t
1#
#280000
0#
#285000
b11101 t
1#
#290000
0#
#295000
b11110 t
1#
#300000
0#
#305000
b11111 t
1#
#310000
0#
#315000
b100000 t
1#
#320000
0#
#325000
b100001 t
1#
#330000
0#
#335000
b100010 t
1#
#340000
0#
#345000
b100011 t
1#
#350000
0#
#355000
b100100 t
1#
#360000
0#
#365000
b100101 t
1#
#370000
0#
#375000
b100110 t
1#
#380000
0#
#385000
b100111 t
1#
#390000
0#
#395000
b101000 t
1#
#400000
0#
#405000
b101001 t
1#
#410000
0#
#415000
b101010 t
1#
#420000
0#
#425000
b101011 t
1#
#430000
0#
#435000
b101100 t
1#
#440000
0#
#445000
b101101 t
1#
#450000
0#
#455000
b101110 t
1#
#460000
0#
#465000
b101111 t
1#
#470000
0#
#475000
b110000 t
1#
#480000
0#
#485000
b110001 t
1#
#490000
0#
#495000
b110010 t
1#
#500000
0#
#505000
b110011 t
1#
#510000
0#
#515000
b110100 t
1#
#520000
0#
#525000
b110101 t
1#
#530000
0#
#535000
b110110 t
1#
#540000
0#
#545000
b110111 t
1#
#550000
0#
#555000
b111000 t
1#
#560000
0#
#565000
b111001 t
1#
#570000
0#
#575000
b111010 t
1#
#580000
0#
#585000
b111011 t
1#
#590000
0#
#595000
b111100 t
1#
#600000
0#
#605000
b111101 t
1#
#610000
0#
#615000
b111110 t
1#
#620000
0#
#625000
b111111 t
1#
#630000
0#
#635000
b1000000 t
1#
#640000
0#
#645000
b1000001 t
1#
#650000
0#
#655000
b1000010 t
1#
#660000
0#
#665000
b1000011 t
1#
#670000
0#
#675000
b1000100 t
1#
#680000
0#
#685000
b1000101 t
1#
#690000
0#
#695000
b1000110 t
1#
#700000
0#
#705000
b1000111 t
1#
#710000
0#
#715000
b1001000 t
1#
#720000
0#
#725000
b1001001 t
1#
#730000
0#
#735000
b1001010 t
1#
#740000
0#
#745000
b1001011 t
1#
#750000
0#
#755000
b1001100 t
1#
#760000
0#
#765000
b1001101 t
1#
#770000
0#
#775000
b1001110 t
1#
#780000
0#
#785000
b1001111 t
1#
#790000
0#
#795000
b1010000 t
1#
#800000
0#
#805000
b1010001 t
1#
#810000
0#
#815000
b1010010 t
1#
#820000
0#
#825000
b1010011 t
1#
#830000
0#
#835000
b1010100 t
1#
#840000
0#
#845000
b1010101 t
1#
#850000
0#
#855000
b1010110 t
1#
#860000
0#
#865000
b1010111 t
1#
#870000
0#
#875000
b1011000 t
1#
#880000
0#
#885000
b1011001 t
1#
#890000
0#
#895000
b1011010 t
1#
#900000
0#
#905000
b1011011 t
1#
#910000
0#
#915000
b1011100 t
1#
#920000
0#
#925000
b1011101 t
1#
#930000
0#
#935000
b1011110 t
1#
#940000
0#
#945000
b1011111 t
1#
#950000
0#
#955000
b1100000 t
1#
#960000
0#
#965000
b1100001 t
1#
#970000
0#
#975000
b1100010 t
1#
#980000
0#
#985000
b1100011 t
1#
#990000
0#
#995000
b1100100 t
1#
#1000000
0#
#1005000
b1100101 t
1#
#1010000
0#
#1015000
b1100110 t
1#
#1020000
0#
#1025000
b1100111 t
1#
#1030000
0#
#1035000
b1101000 t
1#
#1040000
0#
#1045000
b1101001 t
1#
#1050000
0#
#1055000
b1101010 t
1#
#1060000
0#
#1065000
b1101011 t
1#
#1070000
0#
#1075000
b1101100 t
1#
#1080000
0#
#1085000
b1101101 t
1#
#1090000
0#
#1095000
b1101110 t
1#
#1100000
0#
#1105000
b1101111 t
1#
#1110000
0#
#1115000
b1110000 t
1#
#1120000
0#
#1125000
b1110001 t
1#
#1130000
0#
#1135000
b1110010 t
1#
#1140000
0#
#1145000
b1110011 t
1#
#1150000
0#
#1155000
b1110100 t
1#
#1160000
0#
#1165000
b1110101 t
1#
#1170000
0#
#1175000
b1110110 t
1#
#1180000
0#
#1185000
b1110111 t
1#
#1190000
0#
#1195000
b1111000 t
1#
#1200000
0#
#1205000
b1111001 t
1#
#1210000
0#
#1215000
b1111010 t
1#
#1220000
0#
#1225000
b1111011 t
1#
#1230000
0#
#1235000
b1111100 t
1#
#1240000
0#
#1245000
b1111101 t
1#
#1250000
0#
#1255000
b1111110 t
1#
#1260000
0#
#1265000
b1111111 t
1#
#1270000
0#
#1275000
b10000000 t
1#
#1280000
0#
#1285000
b10000001 t
1#
#1290000
0#
#1295000
b10000010 t
1#
#1300000
0#
#1305000
b10000011 t
1#
#1310000
0#
#1315000
b10000100 t
1#
#1320000
0#
#1325000
b10000101 t
1#
#1330000
0#
#1335000
b10000110 t
1#
#1340000
0#
#1345000
b10000111 t
1#
#1350000
0#
#1355000
b10001000 t
1#
#1360000
0#
#1365000
b10001001 t
1#
#1370000
0#
#1375000
b10001010 t
1#
#1380000
0#
#1385000
b10001011 t
1#
#1390000
0#
#1395000
b10001100 t
1#
#1400000
0#
#1405000
b10001101 t
1#
#1410000
0#
#1415000
b10001110 t
1#
#1420000
0#
#1425000
b10001111 t
1#
#1430000
0#
#1435000
b10010000 t
1#
#1440000
0#
#1445000
b10010001 t
1#
#1450000
0#
#1455000
b10010010 t
1#
#1460000
0#
#1465000
b10010011 t
1#
#1470000
0#
#1475000
b10010100 t
1#
#1480000
0#
#1485000
b10010101 t
1#
#1490000
0#
#1495000
b10010110 t
1#
#1500000
0#
#1505000
b10010111 t
1#
#1510000
0#
#1515000
b10011000 t
1#
#1520000
0#
#1525000
b10011001 t
1#
#1530000
0#
#1535000
b10011010 t
1#
#1540000
0#
#1545000
b10011011 t
1#
#1550000
0#
#1555000
b10011100 t
1#
#1560000
0#
#1565000
b10011101 t
1#
#1570000
0#
#1575000
b10011110 t
1#
#1580000
0#
#1585000
b10011111 t
1#
#1590000
0#
#1595000
b10100000 t
1#
#1600000
0#
#1605000
b10100001 t
1#
#1610000
0#
#1615000
b10100010 t
1#
#1620000
0#
#1625000
b10100011 t
1#
#1630000
0#
#1635000
b10100100 t
1#
#1640000
0#
#1645000
b10100101 t
1#
#1650000
0#
#1655000
b10100110 t
1#
#1660000
0#
#1665000
b10100111 t
1#
#1670000
0#
#1675000
b10101000 t
1#
#1680000
0#
#1685000
b10101001 t
1#
#1690000
0#
#1695000
b10101010 t
1#
#1700000
0#
#1705000
b10101011 t
1#
#1710000
0#
#1715000
b10101100 t
1#
#1720000
0#
#1725000
b10101101 t
1#
#1730000
0#
#1735000
b10101110 t
1#
#1740000
0#
#1745000
b10101111 t
1#
#1750000
0#
#1755000
b10110000 t
1#
#1760000
0#
#1765000
b10110001 t
1#
#1770000
0#
#1775000
b10110010 t
1#
#1780000
0#
#1785000
b10110011 t
1#
#1790000
0#
#1795000
b10110100 t
1#
#1800000
0#
#1805000
b10110101 t
1#
#1810000
0#
#1815000
b10110110 t
1#
#1820000
0#
#1825000
b10110111 t
1#
#1830000
0#
#1835000
b10111000 t
1#
#1840000
0#
#1845000
b10111001 t
1#
#1850000
0#
#1855000
b10111010 t
1#
#1860000
0#
#1865000
b10111011 t
1#
#1870000
0#
#1875000
b10111100 t
1#
#1880000
0#
#1885000
b10111101 t
1#
#1890000
0#
#1895000
b10111110 t
1#
#1900000
0#
#1905000
b10111111 t
1#
#1910000
0#
#1915000
b11000000 t
1#
#1920000
0#
#1925000
b11000001 t
1#
#1930000
0#
#1935000
b11000010 t
1#
#1940000
0#
#1945000
b11000011 t
1#
#1950000
0#
#1955000
b11000100 t
1#
#1960000
0#
#1965000
b11000101 t
1#
#1970000
0#
#1975000
b11000110 t
1#
#1980000
0#
#1985000
b11000111 t
1#
#1990000
0#
#1995000
b11001000 t
1#
#2000000
0#
#2005000
b11001001 t
1#
#2010000
0#
#2015000
b11001010 t
1#
#2020000
0#
#2025000
b11001011 t
1#
#2030000
0#
#2035000
b11001100 t
1#
#2040000
0#
#2045000
b11001101 t
1#
#2050000
0#
#2055000
b11001110 t
1#
#2060000
0#
#2065000
b11001111 t
1#
#2070000
0#
#2075000
b11010000 t
1#
#2080000
0#
#2085000
b11010001 t
1#
#2090000
0#
#2095000
b11010010 t
1#
#2100000
0#
#2105000
b11010011 t
1#
#2110000
0#
#2115000
b11010100 t
1#
#2120000
0#
#2125000
b11010101 t
1#
#2130000
0#
#2135000
b11010110 t
1#
#2140000
0#
#2145000
b11010111 t
1#
#2150000
0#
#2155000
b11011000 t
1#
#2160000
0#
#2165000
b11011001 t
1#
#2170000
0#
#2175000
b11011010 t
1#
#2180000
0#
#2185000
b11011011 t
1#
#2190000
0#
#2195000
b11011100 t
1#
#2200000
0#
#2205000
b11011101 t
1#
#2210000
0#
#2215000
b11011110 t
1#
#2220000
0#
#2225000
b11011111 t
1#
#2230000
0#
#2235000
b11100000 t
1#
#2240000
0#
#2245000
b11100001 t
1#
#2250000
0#
#2255000
b11100010 t
1#
#2260000
0#
#2265000
b11100011 t
1#
#2270000
0#
#2275000
b11100100 t
1#
#2280000
0#
#2285000
b11100101 t
1#
#2290000
0#
#2295000
b11100110 t
1#
#2300000
0#
#2305000
b11100111 t
1#
#2310000
0#
#2315000
b11101000 t
1#
#2320000
0#
#2325000
b11101001 t
1#
#2330000
0#
#2335000
b11101010 t
1#
#2340000
0#
#2345000
b11101011 t
1#
#2350000
0#
#2355000
b11101100 t
1#
#2360000
0#
#2365000
b11101101 t
1#
#2370000
0#
#2375000
b11101110 t
1#
#2380000
0#
#2385000
b11101111 t
1#
#2390000
0#
#2395000
b11110000 t
1#
#2400000
0#
#2405000
b11110001 t
1#
#2410000
0#
#2415000
b11110010 t
1#
#2420000
0#
#2425000
b11110011 t
1#
#2430000
0#
#2435000
b11110100 t
1#
#2440000
0#
#2445000
b11110101 t
1#
#2450000
0#
#2455000
b11110110 t
1#
#2460000
0#
#2465000
b11110111 t
1#
#2470000
0#
#2475000
b11111000 t
1#
#2480000
0#
#2485000
b11111001 t
1#
#2490000
0#
#2495000
b11111010 t
1#
#2500000
0#
#2505000
b11111011 t
1#
#2510000
0#
#2515000
b11111100 t
1#
#2520000
0#
#2525000
b11111101 t
1#
#2530000
0#
#2535000
b11111110 t
1#
#2540000
0#
#2545000
b11111111 t
1#
#2550000
0#
#2555000
b100000000 t
1#
#2560000
0#
#2565000
b100000001 t
1#
#2570000
0#
#2575000
b100000010 t
1#
#2580000
0#
#2585000
b100000011 t
1#
#2590000
0#
#2595000
b100000100 t
1#
#2600000
0#
#2605000
b100000101 t
1#
#2610000
0#
#2615000
b100000110 t
1#
#2620000
0#
#2625000
b100000111 t
1#
#2630000
0#
#2635000
b100001000 t
1#
#2640000
0#
#2645000
b100001001 t
1#
#2650000
0#
#2655000
b100001010 t
1#
#2660000
0#
#2665000
b100001011 t
1#
#2670000
0#
#2675000
b100001100 t
1#
#2680000
0#
#2685000
b100001101 t
1#
#2690000
0#
#2695000
b100001110 t
1#
#2700000
0#
#2705000
b100001111 t
1#
#2710000
0#
#2715000
b100010000 t
1#
#2720000
0#
#2725000
b100010001 t
1#
#2730000
0#
#2735000
b100010010 t
1#
#2740000
0#
#2745000
b100010011 t
1#
#2750000
0#
#2755000
b100010100 t
1#
#2760000
0#
#2765000
b100010101 t
1#
#2770000
0#
#2775000
b100010110 t
1#
#2780000
0#
#2785000
b100010111 t
1#
#2790000
0#
#2795000
b100011000 t
1#
#2800000
0#
#2805000
b100011001 t
1#
#2810000
0#
#2815000
b100011010 t
1#
#2820000
0#
#2825000
b100011011 t
1#
#2830000
0#
#2835000
b100011100 t
1#
#2840000
0#
#2845000
b100011101 t
1#
#2850000
0#
#2855000
b100011110 t
1#
#2860000
0#
#2865000
b100011111 t
1#
#2870000
0#
#2875000
b100100000 t
1#
#2880000
0#
#2885000
b100100001 t
1#
#2890000
0#
#2895000
b100100010 t
1#
#2900000
0#
#2905000
b100100011 t
1#
#2910000
0#
#2915000
b100100100 t
1#
#2920000
0#
#2925000
b100100101 t
1#
#2930000
0#
#2935000
b100100110 t
1#
#2940000
0#
#2945000
b100100111 t
1#
#2950000
0#
#2955000
b100101000 t
1#
#2960000
0#
#2965000
b100101001 t
1#
#2970000
0#
#2975000
b100101010 t
1#
#2980000
0#
#2985000
b100101011 t
1#
#2990000
0#
#2995000
b100101100 t
1#
#3000000
0#
#3005000
b100101101 t
1#
#3010000
0#
#3015000
b100101110 t
1#
#3020000
0#
#3025000
b100101111 t
1#
#3030000
0#
#3035000
b100110000 t
1#
#3040000
0#
#3045000
b100110001 t
1#
#3050000
0#
#3055000
b100110010 t
1#
#3060000
0#
#3065000
b100110011 t
1#
#3070000
0#
#3075000
b100110100 t
1#
#3080000
0#
#3085000
b100110101 t
1#
#3090000
0#
#3095000
b100110110 t
1#
#3100000
0#
#3105000
b100110111 t
1#
#3110000
0#
#3115000
b100111000 t
1#
#3120000
0#
#3125000
b100111001 t
1#
#3130000
0#
#3135000
b100111010 t
1#
#3140000
0#
#3145000
b100111011 t
1#
#3150000
0#
#3155000
b100111100 t
1#
#3160000
0#
#3165000
b100111101 t
1#
#3170000
0#
#3175000
b100111110 t
1#
#3180000
0#
#3185000
b100111111 t
1#
#3190000
0#
#3195000
b101000000 t
1#
#3200000
0#
#3205000
b101000001 t
1#
#3210000
0#
#3215000
b101000010 t
1#
#3220000
0#
#3225000
b101000011 t
1#
#3230000
0#
#3235000
b101000100 t
1#
#3240000
0#
#3245000
b101000101 t
1#
#3250000
0#
#3255000
b101000110 t
1#
#3260000
0#
#3265000
b101000111 t
1#
#3270000
0#
#3275000
b101001000 t
1#
#3280000
0#
#3285000
b101001001 t
1#
#3290000
0#
#3295000
b101001010 t
1#
#3300000
0#
#3305000
b101001011 t
1#
#3310000
0#
#3315000
b101001100 t
1#
#3320000
0#
#3325000
b101001101 t
1#
#3330000
0#
#3335000
b101001110 t
1#
#3340000
0#
#3345000
b101001111 t
1#
#3350000
0#
#3355000
b101010000 t
1#
#3360000
0#
#3365000
b101010001 t
1#
#3370000
0#
#3375000
b101010010 t
1#
#3380000
0#
#3385000
b101010011 t
1#
#3390000
0#
#3395000
b101010100 t
1#
#3400000
0#
#3405000
b101010101 t
1#
#3410000
0#
#3415000
b101010110 t
1#
#3420000
0#
#3425000
b101010111 t
1#
#3430000
0#
#3435000
b101011000 t
1#
#3440000
0#
#3445000
b101011001 t
1#
#3450000
0#
#3455000
b101011010 t
1#
#3460000
0#
#3465000
b101011011 t
1#
#3470000
0#
#3475000
b101011100 t
1#
#3480000
0#
