gcode_sender.v
module gcode_sender(
    input wire clk,
    input wire reset,
    input wire tx_ready,
    output reg tx_valid = 0,
    output reg [7:0] tx_data = 0
);

    reg [7:0] gcode_bytes [0:17];
    reg [5:0] index = 0;
    reg first_cycle = 1'b1;
    reg prev_ready = 0;
    reg see_ready = 0;
    initial begin
        gcode_bytes[0] = "G";
        gcode_bytes[1] = "9";
        gcode_bytes[2] = "0";
        gcode_bytes[3] = "\n";
        gcode_bytes[4] = "G";
        gcode_bytes[5] = "2";
        gcode_bytes[6] = "1";
        gcode_bytes[7] = "\n";
        gcode_bytes[8] = "G";
        gcode_bytes[9] = "1";
        gcode_bytes[10] = " ";
        gcode_bytes[11] = "X";
        gcode_bytes[12] = "0";
        gcode_bytes[13] = " ";
        gcode_bytes[14] = "Y";
        gcode_bytes[15] = "1";
        gcode_bytes[16] = "0";
        gcode_bytes[17] = "\n";
    end
    always @(posedge clk) begin
        prev_ready <= tx_ready;
        if(first_cycle || reset) begin
            see_ready <= tx_ready;
            first_cycle <=0;
        end else begin
            see_ready <= ~prev_ready & tx_ready;
        end
    end
    always @(posedge clk) begin
        if (reset) begin
            index <= 0;
            tx_valid <= 0; 
        end else begin
            tx_valid <=0;
            if (see_ready) begin
                tx_data <= gcode_bytes[index];
                tx_valid <= 1;
                index <= index + 1;
            end
        end
    end

endmodule

uart_transmit.v
module uart_transmit #(
    parameter CLK_HZ = 100_000_000,
    parameter BAUD_RT = 115200,
    parameter DATA_BITS = 8
)(
    input wire clk,
    input wire reset,
    output wire tx_send,
    output wire tx_busy,
    input wire tx_start,
    input wire [7:0] tx_data,
    input wire rx
);
    localparam CYCLES_PER_BIT = CLK_HZ/BAUD_RT;
    localparam COUNT_CYC_BITS = $clog2(CYCLES_PER_BIT);
    // assign baud_clk = BAUD_CLK;
    reg BAUD_CLK = 0;
    reg [COUNT_CYC_BITS-1:0] cycle_counter = 0;
    reg [1:0] state = IDLE;
    reg [3:0] bit_counter;
    reg [7:0] shifted_data;
    reg tx_sdata = 1'b1;

    assign tx_send = tx_sdata;
    assign tx_busy = (state != IDLE);

    localparam IDLE = 2'b00;
    localparam START = 2'b01;
    localparam DATA = 2'b10;
    localparam STOP = 2'b11;

    always @(posedge clk) begin
        if (reset) begin
            cycle_counter <= 0;
            BAUD_CLK <= 0;
        end else begin
            if(cycle_counter == (CYCLES_PER_BIT -1)) begin
                cycle_counter <= 0;
                BAUD_CLK <= 1;
            end else begin
                cycle_counter <= cycle_counter +1;
                BAUD_CLK <= 0;
            end
        end
    end

    always @(posedge clk) begin
        if (reset) begin
            bit_counter <= 0;
            tx_sdata <= 1;
            state <= IDLE;
        end else begin
        case (state) 
            IDLE: begin
                bit_counter <= 0;
                if(tx_start)begin
                    shifted_data <= tx_data;
                    state <= START;
                end
            end
            START: begin
                if(BAUD_CLK) begin
                    tx_sdata <= 1'b0;
                    state <= DATA;
                end
            end
            DATA: begin
                if(BAUD_CLK) begin
                    tx_sdata <= shifted_data[0];
                    shifted_data <= {1'b0, shifted_data[7:1]};
                    if(bit_counter == 7) begin
                        state <= STOP;
                        bit_counter <=0;
                    end else begin
                        bit_counter <= bit_counter +1;
                    end
                end
            end
            STOP: begin
                if(BAUD_CLK) begin
                    tx_sdata <= 1'b1;
                    state <= IDLE;
                end
            end
        endcase
        end
    end

endmodule

sending_tx.v
module sending_tx(
    input wire clk,
    input wire reset,
    output wire tx,
    output wire ledone,
    output wire ledtwo
);
    assign ledone = reset;
    assign ledtwo = clk;
    wire uart_tx_busy;
    wire tx_valid;
    wire baud_clk;
    // reg [7:0] test_byte = "H";
    // reg send = 0;
    wire[7:0] test_letter;

    uart_transmit uut(.clk(clk), 
            .reset(reset), 
            .tx_send(tx), 
            .tx_busy(uart_tx_busy), 
            .tx_start(tx_valid), 
            .tx_data(test_letter));

    // always @(posedge clk) begin
    //     if (!uart_tx_busy) begin
    //         send <= 1;
    //     end else begin
    //         send <= 0;
    //     end
    // end
    gcode_sender getting_gcode(.clk(clk), 
            .reset(reset),
            .tx_ready(!uart_tx_busy),
            .tx_valid(tx_valid),
            .tx_data(test_letter));
endmodule

send_tx_tb.v
`timescale 1ns/1ps

module send_tx_tb;
    reg clk, reset;
    wire tx, rx;

    sending_tx transmitTest(.clk(clk), .reset(reset), .tx(tx));

    initial begin
        clk = 0;
        forever #5 clk = ~clk;
    end
    initial begin
        #1000000;
        $finish;
    end
    initial begin
        $dumpfile("sending_tx.vcd");
        $dumpvars(0, send_tx_tb);
    end

endmodule

serialSendTest/serialSendTest.sim/sim_1/behav/xsim/sending_tx.vcd
$date
   Sun Nov 30 14:00:42 2025
$end
$version
  2020.2
$end
$timescale
  1ps
$end
$scope module send_tx_tb $end
$var reg 1 ! clk $end
$var reg 1 " reset $end
$var wire 1 # tx $end
$var wire 1 $ rx $end
$scope module transmitTest $end
$var wire 1 % clk $end
$var wire 1 & reset $end
$var wire 1 # tx $end
$var wire 1 ' ledone $end
$var wire 1 ( ledtwo $end
$var wire 1 ) uart_tx_busy $end
$var wire 1 * tx_valid $end
$var wire 1 + baud_clk $end
$var wire 8 , test_letter [7:0] $end
$scope module uut $end
$var wire 1 % clk $end
$var wire 1 & reset $end
$var wire 1 # tx_send $end
$var wire 1 ) tx_busy $end
$var wire 1 * tx_start $end
$var wire 8 , tx_data [7:0] $end
$var reg 1 - BAUD_CLK $end
$var reg 10 . cycle_counter [9:0] $end
$var reg 2 / state [1:0] $end
$var reg 4 0 bit_counter [3:0] $end
$var reg 8 1 shifted_data [7:0] $end
$var reg 1 2 tx_sdata $end
$upscope $end
$scope module getting_gcode $end
$var wire 1 % clk $end
$var wire 1 & reset $end
$var wire 1 3 tx_ready $end
$var reg 1 4 tx_valid $end
$var reg 8 5 tx_data [7:0] $end
$var reg 6 6 index [5:0] $end
$var reg 1 7 first_cycle $end
$var reg 1 8 prev_ready $end
$var reg 1 9 see_ready $end
$upscope $end
$upscope $end
$upscope $end
$enddefinitions $end
#0
$dumpvars
0!
0"
1#
z$
0%
0&
1'
0(
0)
0*
z+
b0 ,
0-
b0 .
b0 /
b0 0
bx 1
12
13
04
b0 5
b0 6
17
08
09
$end
#5000
1!
1%
1(
b1 .
07
18
19
#10000
0!
0%
0(
#15000
1!
1%
1(
1*
b1000111 ,
b10 .
14
b1000111 5
b1 6
09
#20000
0!
0%
0(
#25000
1!
1%
1(
1)
0*
b11 .
b1 /
b1000111 1
03
04
#30000
0!
0%
0(
#35000
1!
1%
1(
b100 .
08
#40000
0!
0%
0(
#45000
1!
1%
1(
b101 .
#50000
0!
0%
0(
#55000
1!
1%
1(
b110 .
#60000
0!
0%
0(
#65000
1!
1%
1(
b111 .
#70000
0!
0%
0(
#75000
1!
1%
1(
b1000 .
#80000
0!
0%
0(
#85000
1!
1%
1(
b1001 .
#90000
0!
0%
0(
#95000
1!
1%
1(
b1010 .
#100000
0!
0%
0(
#105000
1!
1%
1(
b1011 .
#110000
0!
0%
0(
#115000
1!
1%
1(
b1100 .
#120000
0!
0%
0(
#125000
1!
1%
1(
b1101 .
#130000
0!
0%
0(
#135000
1!
1%
1(
b1110 .
#140000
0!
0%
0(
#145000
1!
1%
1(
b1111 .
#150000
0!
0%
0(
#155000
1!
1%
1(
b10000 .
#160000
0!
0%
0(
#165000
1!
1%
1(
b10001 .
#170000
0!
0%
0(
#175000
1!
1%
1(
b10010 .
#180000
0!
0%
0(
#185000
1!
1%
1(
b10011 .
#190000
0!
0%
0(
#195000
1!
1%
1(
b10100 .
#200000
0!
0%
0(
#205000
1!
1%
1(
b10101 .
#210000
0!
0%
0(
#215000
1!
1%
1(
b10110 .
#220000
0!
0%
0(
#225000
1!
1%
1(
b10111 .
#230000
0!
0%
0(
#235000
1!
1%
1(
b11000 .
#240000
0!
0%
0(
#245000
1!
1%
1(
b11001 .
#250000
0!
0%
0(
#255000
1!
1%
1(
b11010 .
#260000
0!
0%
0(
#265000
1!
1%
1(
b11011 .
#270000
0!
0%
0(
#275000
1!
1%
1(
b11100 .
#280000
0!
0%
0(
#285000
1!
1%
1(
b11101 .
#290000
0!
0%
0(
#295000
1!
1%
1(
b11110 .
#300000
0!
0%
0(
#305000
1!
1%
1(
b11111 .
#310000
0!
0%
0(
#315000
1!
1%
1(
b100000 .
#320000
0!
0%
0(
#325000
1!
1%
1(
b100001 .
#330000
0!
0%
0(
#335000
1!
1%
1(
b100010 .
#340000
0!
0%
0(
#345000
1!
1%
1(
b100011 .
#350000
0!
0%
0(
#355000
1!
1%
1(
b100100 .
#360000
0!
0%
0(
#365000
1!
1%
1(
b100101 .
#370000
0!
0%
0(
#375000
1!
1%
1(
b100110 .
#380000
0!
0%
0(
#385000
1!
1%
1(
b100111 .
#390000
0!
0%
0(
#395000
1!
1%
1(
b101000 .
#400000
0!
0%
0(
#405000
1!
1%
1(
b101001 .
#410000
0!
0%
0(
#415000
1!
1%
1(
b101010 .
#420000
0!
0%
0(
#425000
1!
1%
1(
b101011 .
#430000
0!
0%
0(
#435000
1!
1%
1(
b101100 .
#440000
0!
0%
0(
#445000
1!
1%
1(
b101101 .
#450000
0!
0%
0(
#455000
1!
1%
1(
b101110 .
#460000
0!
0%
0(
#465000
1!
1%
1(
b101111 .
#470000
0!
0%
0(
#475000
1!
1%
1(
b110000 .
#480000
0!
0%
0(
#485000
1!
1%
1(
b110001 .
#490000
0!
0%
0(
#495000
1!
1%
1(
b110010 .
#500000
0!
0%
0(
#505000
1!
1%
1(
b110011 .
#510000
0!
0%
0(
#515000
1!
1%
1(
b110100 .
#520000
0!
0%
0(
#525000
1!
1%
1(
b110101 .
#530000
0!
0%
0(
#535000
1!
1%
1(
b110110 .
#540000
0!
0%
0(
#545000
1!
1%
1(
b110111 .
#550000
0!
0%
0(
#555000
1!
1%
1(
b111000 .
#560000
0!
0%
0(
#565000
1!
1%
1(
b111001 .
#570000
0!
0%
0(
#575000
1!
1%
1(
b111010 .
#580000
0!
0%
0(
#585000
1!
1%
1(
b111011 .
#590000
0!
0%
0(
#595000
1!
1%
1(
b111100 .
#600000
0!
0%
0(
#605000
1!
1%
1(
b111101 .
#610000
0!
0%
0(
#615000
1!
1%
1(
b111110 .
#620000
0!
0%
0(
#625000
1!
1%
1(
b111111 .
#630000
0!
0%
0(
#635000
1!
1%
1(
b1000000 .
#640000
0!
0%
0(
#645000
1!
1%
1(
b1000001 .
#650000
0!
0%
0(
#655000
1!
1%
1(
b1000010 .
#660000
0!
0%
0(
#665000
1!
1%
1(
b1000011 .
#670000
0!
0%
0(
#675000
1!
1%
1(
b1000100 .
#680000
0!
0%
0(
#685000
1!
1%
1(
b1000101 .
#690000
0!
0%
0(
#695000
1!
1%
1(
b1000110 .
#700000
0!
0%
0(
#705000
1!
1%
1(
b1000111 .
#710000
0!
0%
0(
#715000
1!
1%
1(
b1001000 .
#720000
0!
0%
0(
#725000
1!
1%
1(
b1001001 .
#730000
0!
0%
0(
#735000
1!
1%
1(
b1001010 .
#740000
0!
0%
0(
#745000
1!
1%
1(
b1001011 .
#750000
0!
0%
0(
#755000
1!
1%
1(
b1001100 .
#760000
0!
0%
0(
#765000
1!
1%
1(
b1001101 .
#770000
0!
0%
0(
#775000
1!
1%
1(
b1001110 .
#780000
0!
0%
0(
#785000
1!
1%
1(
b1001111 .
#790000
0!
0%
0(
#795000
1!
1%
1(
b1010000 .
#800000
0!
0%
0(
#805000
1!
1%
1(
b1010001 .
#810000
0!
0%
0(
#815000
1!
1%
1(
b1010010 .
#820000
0!
0%
0(
#825000
1!
1%
1(
b1010011 .
#830000
0!
0%
0(
#835000
1!
1%
1(
b1010100 .
#840000
0!
0%
0(
#845000
1!
1%
1(
b1010101 .
#850000
0!
0%
0(
#855000
1!
1%
1(
b1010110 .
#860000
0!
0%
0(
#865000
1!
1%
1(
b1010111 .
#870000
0!
0%
0(
#875000
1!
1%
1(
b1011000 .
#880000
0!
0%
0(
#885000
1!
1%
1(
b1011001 .
#890000
0!
0%
0(
#895000
1!
1%
1(
b1011010 .
#900000
0!
0%
0(
#905000
1!
1%
1(
b1011011 .
#910000
0!
0%
0(
#915000
1!
1%
1(
b1011100 .
#920000
0!
0%
0(
#925000
1!
1%
1(
b1011101 .
#930000
0!
0%
0(
#935000
1!
1%
1(
b1011110 .
#940000
0!
0%
0(
#945000
1!
1%
1(
b1011111 .
#950000
0!
0%
0(
#955000
1!
1%
1(
b1100000 .
#960000
0!
0%
0(
#965000
1!
1%
1(
b1100001 .
#970000
0!
0%
0(
#975000
1!
1%
1(
b1100010 .
#980000
0!
0%
0(
#985000
1!
1%
1(
b1100011 .
#990000
0!
0%
0(
#995000
1!
1%
1(
b1100100 .
#1000000
0!
0%
0(
